{
	"description": "项目配置文件",
	"packOptions": {
		"ignore": []
	},
	"setting": {
		"urlCheck": true,
		"es6": true,
		"enhance": false,
		"postcss": true,
		"preloadBackgroundData": false,
		"minified": true,
		"newFeature": false,
		"coverView": true,
		"nodeModules": false,
		"autoAudits": false,
		"showShadowRootInWxmlPanel": true,
		"scopeDataCheck": false,
		"uglifyFileName": false,
		"checkInvalidKey": true,
		"checkSiteMap": true,
		"uploadWithSourceMap": true,
		"compileHotReLoad": false,
		"babelSetting": {
			"ignore": [],
			"disablePlugins": [],
			"outputPath": ""
		},
		"useIsolateContext": true,
		"useCompilerModule": true,
		"userConfirmedUseCompilerModuleSwitch": false
	},
	"compileType": "miniprogram",
	"libVersion": "2.12.1",
	"appid": "wx5241bbd2329b00cd",
	"projectname": "%E6%88%90%E9%95%BF%E8%AF%BE%E7%A8%8B%E8%A1%A81",
	"debugOptions": {
		"hidedInDevtools": []
	},
	"scripts": {},
	"isGameTourist": false,
	"simulatorType": "wechat",
	"simulatorPluginLibVersion": {},
	"condition": {
		"search": {
			"current": -1,
			"list": []
		},
		"conversation": {
			"current": -1,
			"list": []
		},
		"plugin": {
			"current": -1,
			"list": []
		},
		"game": {
			"current": -1,
			"list": []
		},
		"gamePlugin": {
			"current": -1,
			"list": []
		},
		"miniprogram": {
			"current": -1,
			"list": [
				{
					"id": -1,
					"name": "登录",
					"pathName": "pages/login/login",
					"query": "",
					"scene": null
				},
				{
					"id": 1,
					"name": "个人中心",
					"pathName": "pages/uers/uers",
					"query": "",
					"scene": null
				}
			]
		}
	}
}